uav_api/__init__.py
uav_api/api_app.py
uav_api/args.py
uav_api/copter.py
uav_api/copter_connection.py
uav_api/log.py
uav_api/run_api.py
uav_api/setup.py
uav_api/classes/__init__.py
uav_api/classes/pos.py
uav_api/routers/__init__.py
uav_api/routers/command.py
uav_api/routers/mission.py
uav_api/routers/movement.py
uav_api/routers/peripherical.py
uav_api/routers/telemetry.py
uav_api-0.0.5.dist-info/METADATA
uav_api-0.0.5.dist-info/WHEEL
uav_api-0.0.5.dist-info/entry_points.txt
uav_api-0.0.5.dist-info/top_level.txt
uav_api-0.0.5.dist-info/RECORD
