Metadata-Version: 2.4
Name: uav_api
Version: 0.0.5
Summary: Uav_api is a python package that provides a HTTP interface for MAVLink commands for ardupilot vehicles
Author-email: Francisco Meirelles Fleury <franmeifleury@gmail.com>
Project-URL: Homepage, https://github.com/Project-GrADyS/uav_api
Keywords: mavlink,http,simulation,gradys,LAC,PUC,drone,ardupilot
Classifier: Programming Language :: Python :: 3
Classifier: License :: OSI Approved :: MIT License
Classifier: Operating System :: OS Independent
Requires-Python: >=3.8
Requires-Dist: fastapi>=0.115.4
Requires-Dist: MAVProxy>=1.8.71
Requires-Dist: pydantic>=2.9.2
Requires-Dist: pymavlink>=2.4.41
Requires-Dist: uvicorn>=0.32.0
Requires-Dist: future>=1.0.0
Requires-Dist: pexpect>=4.9.0
